paka.breadcrumbs-1.3.2-py3.5-nspkg.pth
paka/breadcrumbs/__init__.py
paka.breadcrumbs-1.3.2.dist-info/DESCRIPTION.rst
paka.breadcrumbs-1.3.2.dist-info/METADATA
paka.breadcrumbs-1.3.2.dist-info/RECORD
paka.breadcrumbs-1.3.2.dist-info/WHEEL
paka.breadcrumbs-1.3.2.dist-info/metadata.json
paka.breadcrumbs-1.3.2.dist-info/namespace_packages.txt
paka.breadcrumbs-1.3.2.dist-info/top_level.txt
