Metadata-Version: 2.0
Name: paka.breadcrumbs
Version: 1.3.2
Summary: UNKNOWN
Home-page: https://github.com/PavloKapyshin/paka.breadcrumbs
Author: Pavlo Kapyshin
Author-email: i@93z.org
License: BSD
Keywords: site breadcrumbs navigation
Platform: UNKNOWN
Classifier: Development Status :: 4 - Beta
Classifier: Intended Audience :: Developers
Classifier: License :: OSI Approved :: BSD License
Classifier: Programming Language :: Python :: 2
Classifier: Programming Language :: Python :: 2.7
Classifier: Programming Language :: Python :: 3
Classifier: Programming Language :: Python :: 3.5
Classifier: Programming Language :: Python :: Implementation :: CPython
Classifier: Programming Language :: Python :: Implementation :: PyPy
Requires-Dist: markupsafe
Provides-Extra: testing
Requires-Dist: mako; extra == 'testing'
